odoo/addons/ssi_accountant_general_audit_ws_ra150/README.rst
odoo/addons/ssi_accountant_general_audit_ws_ra150/__init__.py
odoo/addons/ssi_accountant_general_audit_ws_ra150/__manifest__.py
odoo/addons/ssi_accountant_general_audit_ws_ra150/data/accountant_business_process_data.xml
odoo/addons/ssi_accountant_general_audit_ws_ra150/data/accountant_financial_report_preparation_data.xml
odoo/addons/ssi_accountant_general_audit_ws_ra150/data/accountant_fraud_factor_data.xml
odoo/addons/ssi_accountant_general_audit_ws_ra150/data/accountant_general_audit_worksheet_type_data.xml
odoo/addons/ssi_accountant_general_audit_ws_ra150/data/approval_template_data.xml
odoo/addons/ssi_accountant_general_audit_ws_ra150/data/ir_sequence_data.xml
odoo/addons/ssi_accountant_general_audit_ws_ra150/data/policy_template_data.xml
odoo/addons/ssi_accountant_general_audit_ws_ra150/data/sequence_template_data.xml
odoo/addons/ssi_accountant_general_audit_ws_ra150/models/__init__.py
odoo/addons/ssi_accountant_general_audit_ws_ra150/models/accountant_business_process.py
odoo/addons/ssi_accountant_general_audit_ws_ra150/models/accountant_financial_report_preparation.py
odoo/addons/ssi_accountant_general_audit_ws_ra150/models/accountant_fraud_factor.py
odoo/addons/ssi_accountant_general_audit_ws_ra150/models/accountant_general_audit.py
odoo/addons/ssi_accountant_general_audit_ws_ra150/models/accountant_general_audit_standard_detail.py
odoo/addons/ssi_accountant_general_audit_ws_ra150/models/accountant_relevant_regulation.py
odoo/addons/ssi_accountant_general_audit_ws_ra150/models/ws_ra150.py
odoo/addons/ssi_accountant_general_audit_ws_ra150/models/ws_ra1501.py
odoo/addons/ssi_accountant_general_audit_ws_ra150/models/ws_ra1502.py
odoo/addons/ssi_accountant_general_audit_ws_ra150/models/ws_ra1503.py
odoo/addons/ssi_accountant_general_audit_ws_ra150/models/ws_ra1503_business_process.py
odoo/addons/ssi_accountant_general_audit_ws_ra150/models/ws_ra1503_expert.py
odoo14_addon_ssi_accountant_general_audit_ws_ra150-14.0.1.7.2.dev1.dist-info/METADATA
odoo14_addon_ssi_accountant_general_audit_ws_ra150-14.0.1.7.2.dev1.dist-info/WHEEL
odoo14_addon_ssi_accountant_general_audit_ws_ra150-14.0.1.7.2.dev1.dist-info/top_level.txt
odoo14_addon_ssi_accountant_general_audit_ws_ra150-14.0.1.7.2.dev1.dist-info/RECORD
